__init__.py
kithub.py
kithub-0.1.1.dist-info/LICENSE
kithub-0.1.1.dist-info/WHEEL
kithub-0.1.1.dist-info/METADATA
kithub-0.1.1.dist-info/RECORD
