Metadata-Version: 2.1
Name: kithub
Version: 0.1.1
Summary: KitHub is a powerful framework for creating and managing tool-based APIs. It integrates seamlessly with LangChain tools and provides a simple interface for exposing these tools as API endpoints.
License: MIT
Keywords: langchain,api,fastapi,tool
Author: Uria Franko
Author-email: uriafranko@gmail.com
Requires-Python: >=3.9,<4.0
Classifier: License :: OSI Approved :: MIT License
Classifier: Programming Language :: Python :: 3
Classifier: Programming Language :: Python :: 3.9
Classifier: Programming Language :: Python :: 3.10
Classifier: Programming Language :: Python :: 3.11
Requires-Dist: fastapi (>=0.111.0,<0.112.0)
Requires-Dist: langchain-community (>=0.2.5,<0.3.0)
Requires-Dist: langchain-core (>=0.2.9,<0.3.0)
